cts_smsteknik-1.0.7.dist-info/DESCRIPTION.rst
cts_smsteknik-1.0.7.dist-info/METADATA
cts_smsteknik-1.0.7.dist-info/RECORD
cts_smsteknik-1.0.7.dist-info/WHEEL
cts_smsteknik-1.0.7.dist-info/entry_points.txt
cts_smsteknik-1.0.7.dist-info/metadata.json
cts_smsteknik-1.0.7.dist-info/top_level.txt
smsteknik/__init__.py
smsteknik/exc.py
smsteknik/smsteknik.py
smsteknik/utils.py
