Metadata-Version: 2.0
Name: cts-smsteknik
Version: 1.0.7
Summary: Unofficial SMS Teknik client
Home-page: http://cross-solutions.com
Author: Cross Solutions
Author-email: UNKNOWN
License: ISC
Platform: UNKNOWN
Classifier: Development Status :: 5 - Production/Stable
Classifier: Intended Audience :: Developers
Classifier: Programming Language :: Python :: 2
Classifier: Programming Language :: Python :: 2.6
Classifier: Programming Language :: Python :: 2.7
Classifier: License :: OSI Approved :: ISC License (ISCL)
Classifier: Topic :: Communications :: Telephony
